sinum/__init__.py
sinum/armstrong.py
sinum/even.py
sinum/factor.py
sinum/fibonacci.py
sinum/natural.py
sinum/odd.py
sinum/palindrome.py
sinum/primes.py
sinum/whole.py
sinum-0.2.dist-info/LICENSE.md
sinum-0.2.dist-info/METADATA
sinum-0.2.dist-info/WHEEL
sinum-0.2.dist-info/top_level.txt
sinum-0.2.dist-info/RECORD
