Metadata-Version: 2.1
Name: sinum
Version: 0.2
Summary: A Python package for various number-related operations.
Home-page: https://github.com/Saurav-TB-Pandey/sinum-package
Author: Saurav Pandey
Author-email: pandeysaurav878@gmail.com
License: MIT
Keywords: sinum
Platform: UNKNOWN
Requires-Python: >=3.6
License-File: LICENSE.md
